IFE_Surrogate/__init__.py
IFE_Surrogate/DNN/__init__.py
IFE_Surrogate/DNN/parameter_model.py
IFE_Surrogate/GP/__init__.py
IFE_Surrogate/GP/abstract_gp.py
IFE_Surrogate/GP/inference.py
IFE_Surrogate/GP/likelihood.py
IFE_Surrogate/GP/train.py
IFE_Surrogate/GP/kernels/__init__.py
IFE_Surrogate/GP/kernels/base_kernel.py
IFE_Surrogate/GP/kernels/compound_kernels.py
IFE_Surrogate/GP/kernels/compound_kernels_old.py
IFE_Surrogate/GP/kernels/fixed_kernel.py
IFE_Surrogate/GP/kernels/kriging_kernel.py
IFE_Surrogate/GP/kernels/lcm_kernel.py
IFE_Surrogate/GP/kernels/matern.py
IFE_Surrogate/GP/kernels/noise.py
IFE_Surrogate/GP/kernels/rational_quadratic.py
IFE_Surrogate/GP/kernels/rbf.py
IFE_Surrogate/GP/kernels/scale.py
IFE_Surrogate/GP/kernels/spectral_mixture_kernel.py
IFE_Surrogate/GP/models/__init__.py
IFE_Surrogate/GP/models/emm.py
IFE_Surrogate/GP/models/multi_output_gp.py
IFE_Surrogate/GP/models/scalar_gp.py
IFE_Surrogate/GP/models/wideband_gp.py
IFE_Surrogate/utils/__init__.py
IFE_Surrogate/utils/cross_validation.py
IFE_Surrogate/utils/data_loader.py
IFE_Surrogate/utils/fsv.py
IFE_Surrogate/utils/metrics.py
IFE_Surrogate/utils/preprocessing.py
IFE_Surrogate/utils/plotting/__init__.py
IFE_Surrogate/utils/plotting/visualizer.py
examples/__init__.py
ife_surrogate-0.1.2.dist-info/licenses/LICENSE
ife_surrogate-0.1.2.dist-info/METADATA
ife_surrogate-0.1.2.dist-info/WHEEL
ife_surrogate-0.1.2.dist-info/top_level.txt
ife_surrogate-0.1.2.dist-info/RECORD
