Metadata-Version: 2.4
Name: IFE_Surrogate
Version: 0.1.2
Summary: A machine learning library intended for surrogate modeling.
Home-page: https://github.com/your-repo
Author: Your Name
Author-email: your.email@example.com
Classifier: Programming Language :: Python :: 3
Classifier: License :: OSI Approved :: MIT License
Classifier: Operating System :: OS Independent
Requires-Python: >=3.7
License-File: LICENSE
Requires-Dist: absl-py==2.3.0
Requires-Dist: annotated-types==0.7.0
Requires-Dist: anyio==4.9.0
Requires-Dist: asttokens==3.0.0
Requires-Dist: attrs==25.3.0
Requires-Dist: blinker==1.9.0
Requires-Dist: cachetools==5.5.2
Requires-Dist: certifi==2025.7.14
Requires-Dist: charset-normalizer==3.4.2
Requires-Dist: click==8.2.1
Requires-Dist: cloudpickle==3.1.1
Requires-Dist: colorama==0.4.6
Requires-Dist: colorlog==6.9.0
Requires-Dist: comm==0.2.2
Requires-Dist: contourpy==1.3.2
Requires-Dist: cycler==0.12.1
Requires-Dist: debugpy==1.8.14
Requires-Dist: decorator==5.2.1
Requires-Dist: etils==1.12.2
Requires-Dist: executing==2.2.0
Requires-Dist: filelock==3.18.0
Requires-Dist: fonttools==4.58.0
Requires-Dist: fsspec==2025.5.1
Requires-Dist: gitdb==4.0.12
Requires-Dist: GitPython==3.1.44
Requires-Dist: greenlet==3.2.3
Requires-Dist: h11==0.16.0
Requires-Dist: h5py==3.14.0
Requires-Dist: humanize==4.12.3
Requires-Dist: idna==3.10
Requires-Dist: importlib_metadata==8.7.0
Requires-Dist: importlib_resources==6.5.2
Requires-Dist: ipykernel==6.29.5
Requires-Dist: ipython==9.2.0
Requires-Dist: ipython_pygments_lexers==1.1.1
Requires-Dist: itsdangerous==2.2.0
Requires-Dist: jedi==0.19.2
Requires-Dist: Jinja2==3.1.6
Requires-Dist: joblib==1.5.1
Requires-Dist: jupyter_client==8.6.3
Requires-Dist: jupyter_core==5.7.2
Requires-Dist: kiwisolver==1.4.8
Requires-Dist: Mako==1.3.10
Requires-Dist: markdown-it-py==3.0.0
Requires-Dist: MarkupSafe==3.0.2
Requires-Dist: matplotlib==3.10.3
Requires-Dist: matplotlib-inline==0.1.7
Requires-Dist: mdurl==0.1.2
Requires-Dist: mpmath==1.3.0
Requires-Dist: msgpack==1.1.0
Requires-Dist: multipledispatch==1.0.0
Requires-Dist: nest-asyncio==1.6.0
Requires-Dist: networkx==3.4.2
Requires-Dist: numpy==2.2.6
Requires-Dist: opentelemetry-api==1.35.0
Requires-Dist: opentelemetry-sdk==1.35.0
Requires-Dist: opentelemetry-semantic-conventions==0.56b0
Requires-Dist: opt_einsum==3.4.0
Requires-Dist: packaging==25.0
Requires-Dist: pandas==2.2.3
Requires-Dist: parso==0.8.4
Requires-Dist: pillow==11.2.1
Requires-Dist: pip==25.1.1
Requires-Dist: platformdirs==4.3.8
Requires-Dist: plotly==6.2.0
Requires-Dist: prompt_toolkit==3.0.51
Requires-Dist: protobuf==6.31.1
Requires-Dist: psutil==7.0.0
Requires-Dist: pure_eval==0.2.3
Requires-Dist: pyarrow==20.0.0
Requires-Dist: pyasn1==0.6.1
Requires-Dist: pyasn1_modules==0.4.2
Requires-Dist: pydantic==2.11.7
Requires-Dist: pydantic_core==2.33.2
Requires-Dist: Pygments==2.19.1
Requires-Dist: pyparsing==3.2.3
Requires-Dist: python-dateutil==2.9.0.post0
Requires-Dist: pytz==2025.2
Requires-Dist: PyWavelets==1.8.0
Requires-Dist: pywin32==310
Requires-Dist: PyYAML==6.0.2
Requires-Dist: pyzmq==26.4.0
Requires-Dist: requests==2.32.4
Requires-Dist: retrying==1.4.0
Requires-Dist: rich==14.0.0
Requires-Dist: rsa==4.9.1
Requires-Dist: scikit-learn==1.6.1
Requires-Dist: scipy==1.15.3
Requires-Dist: seaborn==0.13.2
Requires-Dist: semver==3.0.4
Requires-Dist: setuptools==80.9.0
Requires-Dist: six==1.17.0
Requires-Dist: smmap==5.0.2
Requires-Dist: sniffio==1.3.1
Requires-Dist: SQLAlchemy==2.0.41
Requires-Dist: sqlparse==0.5.3
Requires-Dist: stack-data==0.6.3
Requires-Dist: starlette==0.47.1
Requires-Dist: sympy==1.14.0
Requires-Dist: threadpoolctl==3.6.0
Requires-Dist: toolz==1.0.0
Requires-Dist: torch==2.7.0
Requires-Dist: torchvision==0.22.0
Requires-Dist: tornado==6.5.1
Requires-Dist: tqdm==4.67.1
Requires-Dist: traitlets==5.14.3
Requires-Dist: typing_extensions==4.13.2
Requires-Dist: typing-inspection==0.4.1
Requires-Dist: tzdata==2025.2
Requires-Dist: urllib3==2.5.0
Requires-Dist: uvicorn==0.35.0
Requires-Dist: waitress==3.0.2
Requires-Dist: wcwidth==0.2.13
Requires-Dist: Werkzeug==3.1.3
Requires-Dist: zipp==3.23.0
Requires-Dist: chex==0.1.89
Requires-Dist: dill==0.4.0
Requires-Dist: fastapi==0.116.1
Requires-Dist: flax==0.10.6
Requires-Dist: ml_dtypes==0.5.1
Requires-Dist: narwhals==1.47.1
Requires-Dist: numpyro==0.18.0
Requires-Dist: optax==0.2.4
Requires-Dist: optuna==4.4.0
Requires-Dist: orbax-checkpoint==0.11.14
Requires-Dist: pysr==1.5.8
Requires-Dist: pyswarms==1.3.0
Requires-Dist: SALib==1.5.1
Requires-Dist: tensorstore==0.1.75
Requires-Dist: treescope==0.1.9
Requires-Dist: wadler_lindig==0.1.6
Dynamic: author
Dynamic: author-email
Dynamic: classifier
Dynamic: description
Dynamic: description-content-type
Dynamic: home-page
Dynamic: license-file
Dynamic: requires-dist
Dynamic: requires-python
Dynamic: summary
